colorsynth/__init__.py
colorsynth/_colorsynth.py
colorsynth/_tests/__init__.py
colorsynth/_tests/test_colorsynth.py
colorsynth/data/std65.txt
colorsynth-0.1.6.dist-info/METADATA
colorsynth-0.1.6.dist-info/WHEEL
colorsynth-0.1.6.dist-info/top_level.txt
colorsynth-0.1.6.dist-info/RECORD
