Metadata-Version: 2.4
Name: colorsynth
Version: 0.1.6
Summary: A Python library for creating false-color images from arrays of spectral radiance
Author-email: "Roy T. Smart" <roytsmart@gmail.com>
Project-URL: Homepage, https://github.com/sun-data/colorsynth
Project-URL: Documentation, https://colorsynth.readthedocs.io/en/latest
Classifier: Programming Language :: Python :: 3
Requires-Python: >=3.10
Requires-Dist: numpy>2
Requires-Dist: numba
Requires-Dist: matplotlib
Requires-Dist: astropy
Provides-Extra: test
Requires-Dist: pytest; extra == "test"
Provides-Extra: doc
Requires-Dist: pytest; extra == "doc"
Requires-Dist: graphviz; extra == "doc"
Requires-Dist: sphinx-autodoc-typehints; extra == "doc"
Requires-Dist: sphinxcontrib-bibtex; extra == "doc"
Requires-Dist: pydata-sphinx-theme; extra == "doc"
Requires-Dist: ipykernel; extra == "doc"
Requires-Dist: jupyter-sphinx; extra == "doc"
Requires-Dist: sphinx-favicon; extra == "doc"
Requires-Dist: scipy; extra == "doc"
Requires-Dist: astroscrappy; extra == "doc"
